GP_Plus_functions/__init__.py
GP_Plus_functions/setup.py.py
GP_Plus_functions/bayesian_optimizations/__init__.py
GP_Plus_functions/bayesian_optimizations/acquisition.py
GP_Plus_functions/bayesian_optimizations/acquisition_1.py
GP_Plus_functions/bayesian_optimizations/bo_steps.py
GP_Plus_functions/bayesian_optimizations/cost_model.py
GP_Plus_functions/kernels/Rough_RBF.py
GP_Plus_functions/kernels/__init__.py
GP_Plus_functions/kernels/matern.py
GP_Plus_functions/kernels/wighted_RBF.py
GP_Plus_functions/kernels/wighted_RBF_Z.py
GP_Plus_functions/likelihoods_noise/__init__.py
GP_Plus_functions/likelihoods_noise/multifidelity.py
GP_Plus_functions/models/GP_Plus.py
GP_Plus_functions/models/__init__.py
GP_Plus_functions/models/gpregression.py
GP_Plus_functions/models/lvgp.py
GP_Plus_functions/optim/__init__.py
GP_Plus_functions/optim/mll_noise_tune.py
GP_Plus_functions/optim/mll_noise_tune2.py
GP_Plus_functions/optim/mll_noise_tune3.py
GP_Plus_functions/optim/mll_scipy.py
GP_Plus_functions/optim/mll_torch.py
GP_Plus_functions/preprocessing/__init__.py
GP_Plus_functions/preprocessing/normalizeX.py
GP_Plus_functions/preprocessing/numericlevels.py
GP_Plus_functions/preprocessing/one_hot_encoding.py
GP_Plus_functions/preprocessing/split.py
GP_Plus_functions/priors/__init__.py
GP_Plus_functions/priors/horseshoe.py
GP_Plus_functions/priors/mollified_uniform.py
GP_Plus_functions/test_functions/Calibration_multi_fidelity.py
GP_Plus_functions/test_functions/__init__.py
GP_Plus_functions/test_functions/multi_fidelity.py
GP_Plus_functions/test_functions/physical.py
GP_Plus_functions/utils/__init__.py
GP_Plus_functions/utils/input_space.py
GP_Plus_functions/utils/interval_score.py
GP_Plus_functions/utils/set_seed.py
GP_Plus_functions/utils/transforms.py
GP_Plus_functions/utils/variables.py
GP_Plus_functions/visual/__init__.py
GP_Plus_functions/visual/plot_latent.py
GP_Plus_functions/visual/plot_latenth.py
GP_Plus_functions/visual/plot_latenth_position.py
GP_Plus_functions-0.1.0.dist-info/METADATA
GP_Plus_functions-0.1.0.dist-info/WHEEL
GP_Plus_functions-0.1.0.dist-info/top_level.txt
GP_Plus_functions-0.1.0.dist-info/RECORD
